SDPA_MR_OFDM/__init__.py
SDPA_MR_OFDM/fields.py
SDPA_MR_OFDM/modulator.py
SDPA_MR_OFDM/pn9.py
SDPA_MR_OFDM/rate_encoder.py
SDPA_MR_OFDM/tests/__init__.py
SDPA_MR_OFDM/tests/test_802_15_4g.py
SDPA_MR_OFDM/tests/test_general.py
SDPA_MR_OFDM-1.0.0.dist-info/METADATA
SDPA_MR_OFDM-1.0.0.dist-info/WHEEL
SDPA_MR_OFDM-1.0.0.dist-info/top_level.txt
SDPA_MR_OFDM-1.0.0.dist-info/RECORD
